st_equation_editor/__init__.py
st_equation_editor/frontend/build/1_index.html
st_equation_editor/frontend/build/asset-manifest.json
st_equation_editor/frontend/build/bootstrap.min.css
st_equation_editor/frontend/build/index.html
st_equation_editor/frontend/build/theme.min.css
st_equation_editor/frontend/build/static/css/main.31df7ead.css
st_equation_editor/frontend/build/static/css/main.31df7ead.css.map
st_equation_editor/frontend/build/static/js/main.89f77cad.js
st_equation_editor/frontend/build/static/js/main.89f77cad.js.LICENSE.txt
st_equation_editor/frontend/build/static/js/main.89f77cad.js.map
streamlit_equation_editor-0.3.19.dist-info/licenses/LICENSE
streamlit_equation_editor-0.3.19.dist-info/METADATA
streamlit_equation_editor-0.3.19.dist-info/WHEEL
streamlit_equation_editor-0.3.19.dist-info/top_level.txt
streamlit_equation_editor-0.3.19.dist-info/RECORD
